flask_mongorest/__init__.py
flask_mongorest/authentication.py
flask_mongorest/exceptions.py
flask_mongorest/methods.py
flask_mongorest/operators.py
flask_mongorest/resources.py
flask_mongorest/utils.py
flask_mongorest/views.py
flask_mongorest/templates/mongorest/debug.html
flask_mongorest_mpcontribs-3.3.0.dist-info/AUTHORS
flask_mongorest_mpcontribs-3.3.0.dist-info/LICENSE
flask_mongorest_mpcontribs-3.3.0.dist-info/METADATA
flask_mongorest_mpcontribs-3.3.0.dist-info/WHEEL
flask_mongorest_mpcontribs-3.3.0.dist-info/top_level.txt
flask_mongorest_mpcontribs-3.3.0.dist-info/RECORD
