Metadata-Version: 2.1
Name: flask-mongorest-mpcontribs
Version: 3.3.0
Summary: Flask restful API framework for MongoDB/MongoEngine
Home-page: http://github.com/tschaume/flask-mongorest
Author: Close.io
Author-email: engineering@close.io
Maintainer: Patrick Huck
Maintainer-email: phuck@lbl.gov
License: BSD
Platform: any
Classifier: Development Status :: 4 - Beta
Classifier: Environment :: Web Environment
Classifier: Intended Audience :: Developers
Classifier: License :: OSI Approved :: BSD License
Classifier: Operating System :: OS Independent
Classifier: Programming Language :: Python
Classifier: Topic :: Internet :: WWW/HTTP :: Dynamic Content
Classifier: Topic :: Software Development :: Libraries :: Python Modules
License-File: LICENSE
License-File: AUTHORS
Requires-Dist: boto3
Requires-Dist: fastnumbers
Requires-Dist: flask-mongoengine-tschaume (>=1.1.0)
Requires-Dist: flask-sse (>=1.0.0)
Requires-Dist: flatten-dict
Requires-Dist: marshmallow-mongoengine (>=0.31.0)
Requires-Dist: mimerender-pr36 (>=0.0.2)
Requires-Dist: pymongo (>=3.12.0)
Requires-Dist: python-dateutil
Requires-Dist: orjson
Requires-Dist: atlasq-tschaume
Provides-Extra: dev
Requires-Dist: flake8 ; extra == 'dev'
Requires-Dist: pytest ; extra == 'dev'
Requires-Dist: pytest-cov ; extra == 'dev'
